{
  "us_markets": [
    {
      "ticker": "^GSPC",
      "name": "S&P 500",
      "price": 7165.08,
      "change": 56.68,
      "change_pct": 0.8,
      "trend_5d": "up"
    },
    {
      "ticker": "^IXIC",
      "name": "NASDAQ",
      "price": 24836.6,
      "change": 398.1,
      "change_pct": 1.63,
      "trend_5d": "up"
    },
    {
      "ticker": "^DJI",
      "name": "Dow Jones",
      "price": 49230.71,
      "change": -79.61,
      "change_pct": -0.16,
      "trend_5d": "down"
    },
    {
      "ticker": "^VIX",
      "name": "VIX",
      "price": 18.71,
      "change": -0.6,
      "change_pct": -3.11,
      "trend_5d": "down"
    },
    {
      "ticker": "^TNX",
      "name": "US 10yr Yield",
      "price": 4.31,
      "change": -0.01,
      "change_pct": -0.23,
      "trend_5d": "up"
    }
  ],
  "asia_markets": [
    {
      "ticker": "^N225",
      "name": "Nikkei 225",
      "price": 59716.18,
      "change": 575.95,
      "change_pct": 0.97,
      "trend_5d": "up"
    },
    {
      "ticker": "^HSI",
      "name": "Hang Seng",
      "price": 25978.07,
      "change": 62.87,
      "change_pct": 0.24,
      "trend_5d": "down"
    },
    {
      "ticker": "000001.SS",
      "name": "Shanghai Composite",
      "price": 4079.9,
      "change": -13.35,
      "change_pct": -0.33,
      "trend_5d": "flat"
    },
    {
      "ticker": "^KS11",
      "name": "KOSPI",
      "price": 6475.63,
      "change": -0.18,
      "change_pct": -0.0,
      "trend_5d": "up"
    }
  ],
  "commodities": [
    {
      "ticker": "GC=F",
      "name": "Gold",
      "price": 4740.9,
      "change_pct": 0.76
    },
    {
      "ticker": "BZ=F",
      "name": "Brent Crude",
      "price": 99.13,
      "change_pct": -5.65
    },
    {
      "ticker": "CL=F",
      "name": "WTI Crude",
      "price": 94.4,
      "change_pct": -1.51
    }
  ],
  "asx200": {
    "level": 8786.5,
    "change_pct": -0.08
  },
  "fx": [
    {
      "ticker": "AUDUSD=X",
      "name": "AUD/USD",
      "current_rate": 0.7133,
      "change_pct": 0.0499
    },
    {
      "ticker": "NZDUSD=X",
      "name": "NZD/USD",
      "current_rate": 0.5881,
      "change_pct": 0.4581
    },
    {
      "ticker": "AUDNZD=X",
      "name": "AUD/NZD",
      "current_rate": 1.2136,
      "change_pct": -0.3613
    }
  ],
  "world_news": [
    {
      "headline": "Foord stars for Arsenal, Kerr equals record in WSL",
      "summary": "Arsenal's Matildas are scenting more Champions League glory after the holders beat OL Lyonnes 2-1 in the first leg of their semi-final at the Emirates Stadium, while Matildas captain Sam Kerr scored twice to keep Chelsea's slim WSL title ambitions alive in a 4-1 win over Everton.",
      "severity": "medium",
      "region": "Global",
      "aus_impact": false,
      "aus_impact_note": "",
      "sources": [
        "ABC Australia"
      ]
    },
    {
      "headline": "Has Iran exposed the limits of what US can achieve by force?",
      "summary": "Political scientist Vali Nasr argues that US and Israeli military options \u2018have come up short&#039;.",
      "severity": "medium",
      "region": "Global",
      "aus_impact": false,
      "aus_impact_note": "",
      "sources": [
        "Al Jazeera"
      ]
    },
    {
      "headline": "Did Trump save eight Iranian women from execution?",
      "summary": "The US president says he saved eight Iranian women from execution, but Iran says otherwise.",
      "severity": "medium",
      "region": "Global",
      "aus_impact": false,
      "aus_impact_note": "",
      "sources": [
        "BBC World"
      ]
    },
    {
      "headline": "Israel issues forced evacuation orders for southern Lebanon in escalation",
      "summary": "Hezbollah rejects allegations from Israeli PM Benjamin Netanyahu that it is undermining the Israel-Lebanon ceasefire.",
      "severity": "medium",
      "region": "Global",
      "aus_impact": false,
      "aus_impact_note": "",
      "sources": [
        "Al Jazeera"
      ]
    },
    {
      "headline": "Kenya\u2019s Sawe shatters two-hour marathon barrier",
      "summary": "Sabastian Sawe of Kenya shattered a world record at the London Marathon.",
      "severity": "medium",
      "region": "Global",
      "aus_impact": false,
      "aus_impact_note": "",
      "sources": [
        "Al Jazeera"
      ]
    },
    {
      "headline": "Hani Watson learned the importance of listening to her rogue bones and 'Nigel'",
      "summary": "When Hani Watson settles under the barbell at the Glasgow Commonwealth Games, she will be lifting more than just the plates on the bar.",
      "severity": "medium",
      "region": "Global",
      "aus_impact": false,
      "aus_impact_note": "",
      "sources": [
        "ABC Australia"
      ]
    },
    {
      "headline": "Trump and officials 'likely' targets of press dinner shooting suspect, authorities believe",
      "summary": "The suspect is expected to be charged with assault of a federal officer and using a firearm during a crime of violence, officials have said.",
      "severity": "medium",
      "region": "Global",
      "aus_impact": false,
      "aus_impact_note": "",
      "sources": [
        "BBC World"
      ]
    },
    {
      "headline": "Accused shooter was targeting Trump and US officials, authorities say",
      "summary": "President Donald Trump says suspect wrote an anti-Christian declaration and is &#039;sick guy&#039;.",
      "severity": "medium",
      "region": "Global",
      "aus_impact": false,
      "aus_impact_note": "",
      "sources": [
        "Al Jazeera"
      ]
    },
    {
      "headline": "No headway in Middle East peace efforts as US and Iran refuse to yield",
      "summary": "<p>Deepening sense of deadlock despite regional diplomacy as Washington and Tehran show no signs of compromise</p><p>Hopes of a breakthrough in negotiations between Iran and the US faded further on Sunday, amid a deepening sense of deadlock in the nearly two-month-long conflict despite intense regional diplomatic activity.</p><p>Washington and Tehran appear unwilling to moderate rhetoric or make concessions, and there are no negotiations scheduled that might bring the war to a definitive end.</p> <a href=\"https://www.theguardian.com/world/2026/apr/26/no-headway-in-middle-east-peace-efforts-as-us-and-iran-refuse-to-yield\">Continue reading...</a>",
      "severity": "medium",
      "region": "Global",
      "aus_impact": false,
      "aus_impact_note": "",
      "sources": [
        "The Guardian"
      ]
    },
    {
      "headline": "First trial of Assad-era Syrian official starts in Damascus",
      "summary": "Syria begun its first public trial of former Assad-era officials, with ex-security chief Atef Najib appearing in court.",
      "severity": "medium",
      "region": "Global",
      "aus_impact": false,
      "aus_impact_note": "",
      "sources": [
        "Al Jazeera"
      ]
    }
  ],
  "narrative": {
    "us_narrative": "Market narrative unavailable.",
    "asia_narrative": "Market narrative unavailable."
  },
  "meta": {
    "briefing_type": "7am",
    "generated_at": "2026-04-27T06:36:40.093652+10:00",
    "date": "2026-04-27",
    "display_date": "Monday 27 April 2026",
    "display_time": "06:36 AM AEST"
  }
}